marblingpy/__init__.py
marblingpy/__main__.py
marblingpy/gen_marbling.py
marblingpy-0.9.2.dist-info/LICENSE.Commercial
marblingpy-0.9.2.dist-info/LICENSE.LGPLv3
marblingpy-0.9.2.dist-info/METADATA
marblingpy-0.9.2.dist-info/WHEEL
marblingpy-0.9.2.dist-info/entry_points.txt
marblingpy-0.9.2.dist-info/top_level.txt
marblingpy-0.9.2.dist-info/RECORD
